{
  "animateLoading": true,
  "backgroundColor": "#faeeda",
  "borderColor": "#ef9f27",
  "borderRadius": "{{appsmith.theme.borderRadius.appBorderRadius}}",
  "borderWidth": "1",
  "bottomRow": 64,
  "boxShadow": "{{appsmith.theme.boxShadow.appBoxShadow}}",
  "children": [
    {
      "borderRadius": "{{appsmith.theme.borderRadius.appBorderRadius}}",
      "bottomRow": 430,
      "boxShadow": "{{appsmith.theme.boxShadow.appBoxShadow}}",
      "canExtend": false,
      "containerStyle": "none",
      "detachFromLayout": true,
      "dynamicBindingPathList": [
        {
          "key": "borderRadius"
        },
        {
          "key": "boxShadow"
        }
      ],
      "dynamicHeight": "AUTO_HEIGHT",
      "flexLayers": [],
      "isLoading": false,
      "isVisible": true,
      "key": "7pgrbgn8k1",
      "leftColumn": 0,
      "maxDynamicHeight": 9000,
      "minDynamicHeight": 4,
      "minHeight": 100,
      "minWidth": 450,
      "mobileBottomRow": 100,
      "mobileLeftColumn": 0,
      "mobileRightColumn": 453,
      "mobileTopRow": 0,
      "needsErrorInfo": false,
      "parentColumnSpace": 1,
      "parentId": "sv3jb1aa62",
      "parentRowSpace": 1,
      "renderMode": "CANVAS",
      "responsiveBehavior": "fill",
      "rightColumn": 453,
      "topRow": 0,
      "type": "CANVAS_WIDGET",
      "version": 1,
      "widgetId": "b4wh6e5awe",
      "widgetName": "Canvas23"
    }
  ],
  "containerStyle": "card",
  "dynamicBindingPathList": [
    {
      "key": "borderRadius"
    },
    {
      "key": "boxShadow"
    },
    {
      "key": "isVisible"
    }
  ],
  "dynamicHeight": "FIXED",
  "dynamicPropertyPathList": [
    {
      "key": "isVisible"
    }
  ],
  "dynamicTriggerPathList": [],
  "flexVerticalAlignment": "stretch",
  "isCanvas": true,
  "isLoading": false,
  "isVisible": "{{JSParts.showBattery()}}",
  "key": "p51vy16sb1",
  "leftColumn": 0,
  "maxDynamicHeight": 9000,
  "minDynamicHeight": 10,
  "minWidth": 450,
  "mobileBottomRow": 31,
  "mobileLeftColumn": 0,
  "mobileRightColumn": 24,
  "mobileTopRow": 21,
  "needsErrorInfo": false,
  "parentColumnSpace": 18.875,
  "parentId": "dvh4v3de8o",
  "parentRowSpace": 10,
  "renderMode": "CANVAS",
  "responsiveBehavior": "fill",
  "rightColumn": 64,
  "shouldScrollContents": true,
  "topRow": 28,
  "type": "CONTAINER_WIDGET",
  "version": 1,
  "widgetId": "sv3jb1aa62",
  "widgetName": "con_battery_checks"
}