{
  "gitSyncId": "6a305b9e0882adc7e482e226_7b03a0e0-4878-4d84-b530-96c1b40171ae",
  "id": "Asset_Bookin_Page_jsAddAsset.confirmAssets",
  "pluginId": "js-plugin",
  "pluginType": "JS",
  "unpublishedAction": {
    "actionConfiguration": {
      "encodeParamsToggle": true,
      "jsArguments": [],
      "paginationType": "NONE",
      "timeoutInMillisecond": 10000
    },
    "collectionId": "Asset_Bookin_Page_jsAddAsset",
    "confirmBeforeExecute": false,
    "datasource": {
      "isAutoGenerated": false,
      "name": "UNUSED_DATASOURCE",
      "pluginId": "js-plugin"
    },
    "dynamicBindingPathList": [
      {
        "key": "body"
      }
    ],
    "fullyQualifiedName": "jsAddAsset.confirmAssets",
    "name": "confirmAssets",
    "pageId": "Asset_Bookin_Page",
    "runBehaviour": "MANUAL",
    "userSetOnLoad": false
  }
}