{
  "gitSyncId": "6a305b9e0882adc7e482e226_00b480df-9eaf-4690-94a8-ac860b607600",
  "id": "Home_HomeActions.onSignOut",
  "pluginId": "js-plugin",
  "pluginType": "JS",
  "unpublishedAction": {
    "actionConfiguration": {
      "encodeParamsToggle": true,
      "jsArguments": [],
      "paginationType": "NONE",
      "timeoutInMillisecond": 10000
    },
    "collectionId": "Home_HomeActions",
    "confirmBeforeExecute": false,
    "datasource": {
      "isAutoGenerated": false,
      "name": "UNUSED_DATASOURCE",
      "pluginId": "js-plugin"
    },
    "dynamicBindingPathList": [
      {
        "key": "body"
      }
    ],
    "fullyQualifiedName": "HomeActions.onSignOut",
    "name": "onSignOut",
    "pageId": "Home",
    "runBehaviour": "MANUAL",
    "userSetOnLoad": false
  }
}