{
  "gitSyncId": "6a305b9e0882adc7e482e226_0916cc65-a83c-4a75-9a6b-d9f7eaf43447",
  "id": "Asset_Page_AssetActions.confirmRepair",
  "pluginId": "js-plugin",
  "pluginType": "JS",
  "unpublishedAction": {
    "actionConfiguration": {
      "encodeParamsToggle": true,
      "jsArguments": [],
      "paginationType": "NONE",
      "timeoutInMillisecond": 10000
    },
    "collectionId": "Asset_Page_AssetActions",
    "confirmBeforeExecute": false,
    "datasource": {
      "isAutoGenerated": false,
      "name": "UNUSED_DATASOURCE",
      "pluginId": "js-plugin"
    },
    "dynamicBindingPathList": [
      {
        "key": "body"
      }
    ],
    "fullyQualifiedName": "AssetActions.confirmRepair",
    "name": "confirmRepair",
    "pageId": "Asset_Page",
    "runBehaviour": "MANUAL",
    "userSetOnLoad": false
  }
}