{
  "gitSyncId": "6a305b9e0882adc7e482e226_61c55ff3-eb71-4f95-b48e-520554f35cd0",
  "id": "Admin_Console_qry_admin_insert_user",
  "pluginId": "postgres-plugin",
  "pluginType": "DB",
  "unpublishedAction": {
    "actionConfiguration": {
      "body": "INSERT INTO users (email, full_name, role, is_active, notes)\nVALUES (\n  '{{Custom_Admin.model.row.email}}',\n  '{{Custom_Admin.model.row.full_name}}',\n  '{{Custom_Admin.model.row.role || \"viewer\"}}',\n  {{Custom_Admin.model.row.is_active !== false}},\n  '{{Custom_Admin.model.row.notes || \"\"}}'\n)\nRETURNING user_id;",
      "encodeParamsToggle": true,
      "paginationType": "NONE",
      "pluginSpecifiedTemplates": [
        {
          "value": true
        }
      ],
      "timeoutInMillisecond": 10000
    },
    "confirmBeforeExecute": false,
    "datasource": {
      "id": "ERP_DB",
      "isAutoGenerated": false,
      "name": "ERP_DB",
      "pluginId": "postgres-plugin"
    },
    "dynamicBindingPathList": [
      {
        "key": "body"
      }
    ],
    "name": "qry_admin_insert_user",
    "pageId": "Admin_Console",
    "runBehaviour": "MANUAL",
    "userSetOnLoad": false
  }
}