{
  "animateLoading": true,
  "borderRadius": "{{appsmith.theme.borderRadius.appBorderRadius}}",
  "bottomRow": 21,
  "dynamicBindingPathList": [
    {
      "key": "truncateButtonColor"
    },
    {
      "key": "fontFamily"
    },
    {
      "key": "borderRadius"
    }
  ],
  "dynamicHeight": "AUTO_HEIGHT",
  "dynamicTriggerPathList": [],
  "fontFamily": "{{appsmith.theme.fontFamily.appFont}}",
  "fontSize": "0.875rem",
  "fontStyle": "BOLD",
  "isLoading": false,
  "isVisible": true,
  "key": "ajyguemwcq",
  "leftColumn": 17,
  "maxDynamicHeight": 9000,
  "minDynamicHeight": 4,
  "minWidth": 450,
  "mobileBottomRow": 14,
  "mobileLeftColumn": 41,
  "mobileRightColumn": 57,
  "mobileTopRow": 10,
  "needsErrorInfo": false,
  "originalBottomRow": 23,
  "originalTopRow": 19,
  "overflow": "NONE",
  "parentColumnSpace": 19.5,
  "parentId": "gszvgh90hy",
  "parentRowSpace": 10,
  "renderMode": "CANVAS",
  "responsiveBehavior": "fill",
  "rightColumn": 23,
  "shouldTruncate": false,
  "text": "Data Bearing",
  "textAlign": "LEFT",
  "textColor": "#858282",
  "topRow": 17,
  "truncateButtonColor": "{{appsmith.theme.colors.primaryColor}}",
  "type": "TEXT_WIDGET",
  "version": 1,
  "widgetId": "9kx5dxfiyu",
  "widgetName": "Text15"
}