{
  "gitSyncId": "6a305b9e0882adc7e482e226_deff0576-c6ae-4dc6-9666-88e852166c99",
  "id": "Waste_Detail_Page_qry_insert_waste_pallet",
  "pluginId": "postgres-plugin",
  "pluginType": "DB",
  "unpublishedAction": {
    "actionConfiguration": {
      "body": "INSERT INTO waste_pallets (\n  waste_id, status, weight_kg, notes, waste_type, created_by, created_at\n) VALUES (\n  '{{qry_get_next_waste_id.data[0].next_waste_id}}',\n  'open',\n  {{this.params.weight}},\n  '{{this.params.notes.replace(/'/g, \"''\")}}',\n  '{{this.params.wasteType}}',\n  '{{this.params.createdBy}}',\n  NOW()\n);",
      "encodeParamsToggle": true,
      "paginationType": "NONE",
      "pluginSpecifiedTemplates": [
        {
          "value": true
        }
      ],
      "timeoutInMillisecond": 10000
    },
    "confirmBeforeExecute": false,
    "datasource": {
      "id": "ERP_DB",
      "isAutoGenerated": false,
      "name": "ERP_DB",
      "pluginId": "postgres-plugin"
    },
    "dynamicBindingPathList": [
      {
        "key": "body"
      }
    ],
    "name": "qry_insert_waste_pallet",
    "pageId": "Waste_Detail_Page",
    "runBehaviour": "MANUAL",
    "userSetOnLoad": false
  }
}