{
  "gitSyncId": "6a305b9e0882adc7e482e226_3342f089-f7b2-42fd-ac37-e43840145961",
  "id": "New_Sale_Page_NavActions.onNavClick",
  "pluginId": "js-plugin",
  "pluginType": "JS",
  "unpublishedAction": {
    "actionConfiguration": {
      "encodeParamsToggle": true,
      "jsArguments": [],
      "paginationType": "NONE",
      "timeoutInMillisecond": 10000
    },
    "collectionId": "New_Sale_Page_NavActions",
    "confirmBeforeExecute": false,
    "datasource": {
      "isAutoGenerated": false,
      "name": "UNUSED_DATASOURCE",
      "pluginId": "js-plugin"
    },
    "dynamicBindingPathList": [
      {
        "key": "body"
      }
    ],
    "fullyQualifiedName": "NavActions.onNavClick",
    "name": "onNavClick",
    "pageId": "New_Sale_Page",
    "runBehaviour": "MANUAL",
    "userSetOnLoad": false
  }
}